[
 {
   "Player": "Nat Berhe",
   "1": 35,
   "2": 17,
   "3": 71,
   "4": null,
   "5": null,
   "6": null,
   "7": null,
   "8": "",
   "9": 3,
   "10": 9,
   "11": 24,
   "12": 5,
   "13": null,
   "14": null,
   "15": null,
   "16": null,
   "17": null,
   "Total": 164
 },
 {
   "Player": "Montori Hughes",
   "1": null,
   "2": null,
   "3": null,
   "4": 10,
   "5": 7,
   "6": null,
   "7": null,
   "8": "",
   "9": null,
   "10": null,
   "11": null,
   "12": null,
   "13": null,
   "14": null,
   "15": null,
   "16": null,
   "17": null,
   "Total": 17
 },
 {
   "Player": "Mark Herzlich",
   "1": 0,
   "2": 0,
   "3": 0,
   "4": 2,
   "5": 4,
   "6": 4,
   "7": 0,
   "8": "",
   "9": 0,
   "10": 0,
   "11": 2,
   "12": 1,
   "13": null,
   "14": null,
   "15": 0,
   "16": 1,
   "17": 1,
   "Total": 15
 },
 {
   "Player": "Devon Kennard",
   "1": 27,
   "2": 10,
   "3": 25,
   "4": 40,
   "5": 22,
   "6": 32,
   "7": 36,
   "8": "",
   "9": 26,
   "10": 39,
   "11": 41,
   "12": 47,
   "13": 42,
   "14": 39,
   "15": 42,
   "16": 35,
   "17": 30,
   "Total": 533
 },
 {
   "Player": "Leon Hall",
   "1": 17,
   "2": 41,
   "3": 46,
   "4": 38,
   "5": 54,
   "6": 52,
   "7": 33,
   "8": "",
   "9": null,
   "10": null,
   "11": null,
   "12": null,
   "13": 16,
   "14": 24,
   "15": 17,
   "16": 14,
   "17": 31,
   "Total": 383
 },
 {
   "Player": "Mykkele Thompson",
   "1": null,
   "2": 0,
   "3": 0,
   "4": 0,
   "5": null,
   "6": null,
   "7": null,
   "8": "",
   "9": null,
   "10": null,
   "11": null,
   "12": null,
   "13": null,
   "14": null,
   "15": null,
   "16": null,
   "17": null,
   "Total": 0
 },
 {
   "Player": "Tavarres King",
   "1": 6,
   "2": 1,
   "3": 3,
   "4": 1,
   "5": 2,
   "6": null,
   "7": null,
   "8": "",
   "9": null,
   "10": 45,
   "11": null,
   "12": null,
   "13": null,
   "14": null,
   "15": null,
   "16": null,
   "17": 18,
   "Total": 76
 },
 {
   "Player": "Bobby Rainey",
   "1": 0,
   "2": null,
   "3": 8,
   "4": 28,
   "5": 28,
   "6": 27,
   "7": 12,
   "8": "",
   "9": null,
   "10": 0,
   "11": 4,
   "12": 6,
   "13": 7,
   "14": 3,
   "15": 0,
   "16": 14,
   "17": 7,
   "Total": 144
 },
 {
   "Player": "Jonathan Casillas",
   "1": 58,
   "2": 41,
   "3": 60,
   "4": 60,
   "5": 61,
   "6": 56,
   "7": 55,
   "8": "",
   "9": 57,
   "10": 37,
   "11": 40,
   "12": 45,
   "13": 57,
   "14": 45,
   "15": 52,
   "16": 34,
   "17": 38,
   "Total": 796
 },
 {
   "Player": "Deontae Skinner",
   "1": null,
   "2": null,
   "3": null,
   "4": null,
   "5": null,
   "6": null,
   "7": null,
   "8": "",
   "9": null,
   "10": null,
   "11": null,
   "12": null,
   "13": 0,
   "14": 0,
   "15": null,
   "16": 0,
   "17": 0,
   "Total": 0
 },
 {
   "Player": "Damon Harrison",
   "1": 51,
   "2": 34,
   "3": 43,
   "4": 44,
   "5": 48,
   "6": 49,
   "7": 45,
   "8": "",
   "9": 46,
   "10": 37,
   "11": 44,
   "12": 47,
   "13": 51,
   "14": 39,
   "15": 31,
   "16": 40,
   "17": 25,
   "Total": 674
 },
 {
   "Player": "Shane Vereen",
   "1": 24,
   "2": 40,
   "3": 36,
   "4": 0,
   "5": null,
   "6": null,
   "7": null,
   "8": "",
   "9": null,
   "10": null,
   "11": null,
   "12": null,
   "13": null,
   "14": 3,
   "15": 14,
   "16": null,
   "17": null,
   "Total": 117
 },
 {
   "Player": "Victor Cruz",
   "1": 50,
   "2": 74,
   "3": 66,
   "4": 66,
   "5": 56,
   "6": 67,
   "7": 41,
   "8": "",
   "9": 15,
   "10": null,
   "11": 60,
   "12": 42,
   "13": 26,
   "14": 49,
   "15": 41,
   "16": 53,
   "17": 60,
   "Total": 766
 },
 {
   "Player": "",
   "1": null,
   "2": null,
   "3": null,
   "4": null,
   "5": null,
   "6": null,
   "7": null,
   "8": "",
   "9": null,
   "10": null,
   "11": null,
   "12": null,
   "13": null,
   "14": null,
   "15": null,
   "16": null,
   "17": null,
   "Total": null
 },
 {
   "Player": "Kelvin Sheppard",
   "1": 59,
   "2": 10,
   "3": 25,
   "4": 39,
   "5": 26,
   "6": 34,
   "7": 23,
   "8": "",
   "9": 20,
   "10": 23,
   "11": 32,
   "12": 25,
   "13": 34,
   "14": 23,
   "15": 26,
   "16": 44,
   "17": 10,
   "Total": 453
 },
 {
   "Player": "Will Tye",
   "1": 25,
   "2": 41,
   "3": 26,
   "4": 52,
   "5": 37,
   "6": 23,
   "7": 23,
   "8": "",
   "9": 46,
   "10": 59,
   "11": 52,
   "12": 49,
   "13": 47,
   "14": 51,
   "15": 42,
   "16": 60,
   "17": 47,
   "Total": 680
 },
 {
   "Player": "Eli Manning",
   "1": 56,
   "2": 79,
   "3": 67,
   "4": 66,
   "5": 56,
   "6": 67,
   "7": 56,
   "8": "",
   "9": 64,
   "10": 75,
   "11": 67,
   "12": 56,
   "13": 60,
   "14": 67,
   "15": 64,
   "16": 89,
   "17": 72,
   "Total": 1061
 },
 {
   "Player": "Eli Apple",
   "1": 56,
   "2": 59,
   "3": 9,
   "4": null,
   "5": 7,
   "6": null,
   "7": 39,
   "8": "",
   "9": 42,
   "10": 58,
   "11": 62,
   "12": 58,
   "13": 73,
   "14": 66,
   "15": 62,
   "16": 55,
   "17": 55,
   "Total": 701
 },
 {
   "Player": "Johnathan Hankins",
   "1": 52,
   "2": 45,
   "3": 62,
   "4": 59,
   "5": 69,
   "6": 55,
   "7": 51,
   "8": "",
   "9": 58,
   "10": 37,
   "11": 44,
   "12": 47,
   "13": 35,
   "14": 39,
   "15": 39,
   "16": 45,
   "17": 27,
   "Total": 764
 },
 {
   "Player": "Jerell Adams",
   "1": null,
   "2": 1,
   "3": null,
   "4": 7,
   "5": 17,
   "6": 11,
   "7": 5,
   "8": "",
   "9": 14,
   "10": 15,
   "11": 17,
   "12": 11,
   "13": 18,
   "14": 21,
   "15": 27,
   "16": 40,
   "17": null,
   "Total": 204
 },
 {
   "Player": "",
   "1": null,
   "2": null,
   "3": null,
   "4": null,
   "5": null,
   "6": null,
   "7": null,
   "8": "",
   "9": null,
   "10": null,
   "11": null,
   "12": null,
   "13": null,
   "14": null,
   "15": null,
   "16": null,
   "17": null,
   "Total": null
 },
 {
   "Player": "Paul Perkins",
   "1": null,
   "2": null,
   "3": 0,
   "4": 15,
   "5": 14,
   "6": 7,
   "7": 15,
   "8": "",
   "9": 22,
   "10": 30,
   "11": 20,
   "12": 22,
   "13": 23,
   "14": 25,
   "15": 25,
   "16": 34,
   "17": 37,
   "Total": 289
 },
 {
   "Player": "Orleans Darkwa",
   "1": 0,
   "2": 5,
   "3": 21,
   "4": 23,
   "5": 14,
   "6": null,
   "7": 0,
   "8": "",
   "9": null,
   "10": 0,
   "11": 0,
   "12": 0,
   "13": null,
   "14": null,
   "15": null,
   "16": null,
   "17": null,
   "Total": 63
 },
 {
   "Player": "Odell Beckham Jr",
   "1": 56,
   "2": 78,
   "3": 67,
   "4": 66,
   "5": 56,
   "6": 55,
   "7": 54,
   "8": "",
   "9": 62,
   "10": 75,
   "11": 67,
   "12": 44,
   "13": 59,
   "14": 67,
   "15": 60,
   "16": 88,
   "17": 48,
   "Total": 1002
 },
 {
   "Player": "Rashad Jennings",
   "1": 32,
   "2": 34,
   "3": null,
   "4": null,
   "5": null,
   "6": 32,
   "7": 28,
   "8": "",
   "9": 37,
   "10": 45,
   "11": 47,
   "12": 28,
   "13": 30,
   "14": 36,
   "15": 25,
   "16": 41,
   "17": 28,
   "Total": 443
 },
 {
   "Player": "Roger Lewis",
   "1": null,
   "2": null,
   "3": null,
   "4": 0,
   "5": 0,
   "6": 14,
   "7": 15,
   "8": "",
   "9": 37,
   "10": 29,
   "11": 5,
   "12": 15,
   "13": 29,
   "14": 10,
   "15": 15,
   "16": 22,
   "17": 16,
   "Total": 207
 },
 {
   "Player": "Andrew Adams",
   "1": null,
   "2": null,
   "3": null,
   "4": null,
   "5": null,
   "6": null,
   "7": null,
   "8": "",
   "9": null,
   "10": null,
   "11": 37,
   "12": 69,
   "13": 57,
   "14": 45,
   "15": 45,
   "16": 40,
   "17": 31,
   "Total": 324
 },
 {
   "Player": "Jason Bromley",
   "1": 16,
   "2": 7,
   "3": 17,
   "4": 16,
   "5": 22,
   "6": 23,
   "7": 19,
   "8": "",
   "9": null,
   "10": 10,
   "11": 13,
   "12": null,
   "13": 16,
   "14": 23,
   "15": 23,
   "16": 16,
   "17": 8,
   "Total": 229
 },
 {
   "Player": "Kerry Wynn",
   "1": 5,
   "2": 5,
   "3": 7,
   "4": 2,
   "5": 10,
   "6": 8,
   "7": 19,
   "8": "",
   "9": null,
   "10": null,
   "11": 0,
   "12": 5,
   "13": 25,
   "14": 4,
   "15": 9,
   "16": 5,
   "17": 12,
   "Total": 116
 },
 {
   "Player": "Larry Donnell",
   "1": 31,
   "2": 43,
   "3": 41,
   "4": 9,
   "5": null,
   "6": 33,
   "7": 31,
   "8": "",
   "9": null,
   "10": 0,
   "11": null,
   "12": 0,
   "13": 1,
   "14": 0,
   "15": 0,
   "16": 0,
   "17": 25,
   "Total": 214
 },
 {
   "Player": "J.T. Thomas",
   "1": 0,
   "2": 0,
   "3": 0,
   "4": 0,
   "5": null,
   "6": null,
   "7": null,
   "8": "",
   "9": null,
   "10": null,
   "11": null,
   "12": null,
   "13": null,
   "14": null,
   "15": null,
   "16": null,
   "17": null,
   "Total": 0
 },
 {
   "Player": "",
   "1": null,
   "2": null,
   "3": null,
   "4": null,
   "5": null,
   "6": null,
   "7": null,
   "8": "",
   "9": null,
   "10": null,
   "11": null,
   "12": null,
   "13": null,
   "14": null,
   "15": null,
   "16": null,
   "17": null,
   "Total": null
 },
 {
   "Player": "Landon Collins",
   "1": 74,
   "2": 62,
   "3": 70,
   "4": 74,
   "5": 80,
   "6": 83,
   "7": 78,
   "8": "",
   "9": 75,
   "10": 58,
   "11": 64,
   "12": 75,
   "13": 73,
   "14": 66,
   "15": 62,
   "16": 56,
   "17": 55,
   "Total": 1105
 },
 {
   "Player": "Romeo Okwara",
   "1": 13,
   "2": 19,
   "3": 7,
   "4": 11,
   "5": 15,
   "6": 14,
   "7": 9,
   "8": "",
   "9": 13,
   "10": 9,
   "11": 15,
   "12": 24,
   "13": 32,
   "14": 60,
   "15": 36,
   "16": 50,
   "17": 41,
   "Total": 368
 },
 {
   "Player": "",
   "1": null,
   "2": null,
   "3": null,
   "4": null,
   "5": null,
   "6": null,
   "7": null,
   "8": "",
   "9": null,
   "10": null,
   "11": null,
   "12": null,
   "13": null,
   "14": null,
   "15": null,
   "16": null,
   "17": null,
   "Total": null
 },
 {
   "Player": "Sterling Shepard",
   "1": 53,
   "2": 75,
   "3": 66,
   "4": 62,
   "5": 56,
   "6": 64,
   "7": 53,
   "8": "",
   "9": 59,
   "10": 71,
   "11": 63,
   "12": 51,
   "13": 60,
   "14": 61,
   "15": 61,
   "16": 88,
   "17": 62,
   "Total": 1005
 },
 {
   "Player": "",
   "1": null,
   "2": null,
   "3": null,
   "4": null,
   "5": null,
   "6": null,
   "7": null,
   "8": "",
   "9": null,
   "10": null,
   "11": null,
   "12": null,
   "13": null,
   "14": null,
   "15": null,
   "16": null,
   "17": null,
   "Total": null
 },
 {
   "Player": "Olivier Vernon",
   "1": 74,
   "2": 60,
   "3": 64,
   "4": 70,
   "5": 72,
   "6": 71,
   "7": 67,
   "8": "",
   "9": 70,
   "10": 56,
   "11": 62,
   "12": 71,
   "13": 72,
   "14": 66,
   "15": 62,
   "16": 56,
   "17": 47,
   "Total": 1040
 },
 {
   "Player": "Will Johnson",
   "1": 0,
   "2": 0,
   "3": 0,
   "4": 0,
   "5": null,
   "6": null,
   "7": null,
   "8": "",
   "9": null,
   "10": null,
   "11": null,
   "12": null,
   "13": null,
   "14": null,
   "15": null,
   "16": null,
   "17": null,
   "Total": 0
 },
 {
   "Player": "Dwayne Harris",
   "1": 1,
   "2": 3,
   "3": 1,
   "4": 1,
   "5": 0,
   "6": 2,
   "7": 3,
   "8": "",
   "9": 16,
   "10": 2,
   "11": 2,
   "12": 6,
   "13": 0,
   "14": 6,
   "15": 5,
   "16": 2,
   "17": 8,
   "Total": 58
 },
 {
   "Player": "Trevin Wade",
   "1": 0,
   "2": 2,
   "3": 43,
   "4": 72,
   "5": 14,
   "6": 40,
   "7": 1,
   "8": "",
   "9": 31,
   "10": 12,
   "11": 15,
   "12": 19,
   "13": 6,
   "14": 10,
   "15": 24,
   "16": 25,
   "17": 41,
   "Total": 355
 },
 {
   "Player": "Darian Thompson",
   "1": 42,
   "2": 45,
   "3": null,
   "4": null,
   "5": null,
   "6": null,
   "7": null,
   "8": "",
   "9": null,
   "10": null,
   "11": null,
   "12": null,
   "13": null,
   "14": null,
   "15": null,
   "16": null,
   "17": null,
   "Total": 87
 },
 {
   "Player": "Eric Pinkins",
   "1": null,
   "2": null,
   "3": null,
   "4": null,
   "5": null,
   "6": null,
   "7": null,
   "8": "",
   "9": null,
   "10": null,
   "11": null,
   "12": null,
   "13": 0,
   "14": 3,
   "15": 0,
   "16": 0,
   "17": 0,
   "Total": 3
 },
 {
   "Player": "",
   "1": null,
   "2": null,
   "3": null,
   "4": null,
   "5": null,
   "6": null,
   "7": null,
   "8": "",
   "9": null,
   "10": null,
   "11": null,
   "12": null,
   "13": null,
   "14": null,
   "15": null,
   "16": null,
   "17": null,
   "Total": null
 },
 {
   "Player": "Robert Thomas",
   "1": null,
   "2": null,
   "3": null,
   "4": null,
   "5": null,
   "6": 14,
   "7": null,
   "8": "",
   "9": 7,
   "10": 4,
   "11": null,
   "12": 12,
   "13": 15,
   "14": 7,
   "15": null,
   "16": 3,
   "17": 6,
   "Total": 68
 },
 {
   "Player": "Nikita Whitlock",
   "1": 0,
   "2": 0,
   "3": 0,
   "4": 0,
   "5": null,
   "6": null,
   "7": null,
   "8": "",
   "9": null,
   "10": null,
   "11": null,
   "12": null,
   "13": null,
   "14": null,
   "15": null,
   "16": null,
   "17": null,
   "Total": 0
 },
 {
   "Player": "",
   "1": null,
   "2": null,
   "3": null,
   "4": null,
   "5": null,
   "6": null,
   "7": null,
   "8": "",
   "9": null,
   "10": null,
   "11": null,
   "12": null,
   "13": null,
   "14": null,
   "15": null,
   "16": null,
   "17": null,
   "Total": null
 },
 {
   "Player": "Jason Pierre-Paul",
   "1": 76,
   "2": 59,
   "3": 71,
   "4": 74,
   "5": 71,
   "6": 77,
   "7": 76,
   "8": "",
   "9": 71,
   "10": 57,
   "11": 59,
   "12": 69,
   "13": 32,
   "14": null,
   "15": null,
   "16": null,
   "17": null,
   "Total": 792
 },
 {
   "Player": "Owamagbe Odighizuwa",
   "1": 17,
   "2": 16,
   "3": 12,
   "4": 11,
   "5": 6,
   "6": 22,
   "7": 11,
   "8": "",
   "9": null,
   "10": 5,
   "11": 12,
   "12": 4,
   "13": null,
   "14": null,
   "15": 15,
   "16": 2,
   "17": 31,
   "Total": 164
 },
 {
   "Player": "Coty Sensabaugh",
   "1": null,
   "2": null,
   "3": null,
   "4": null,
   "5": null,
   "6": 1,
   "7": 0,
   "8": "",
   "9": 9,
   "10": 22,
   "11": 0,
   "12": 30,
   "13": 0,
   "14": 15,
   "15": 25,
   "16": 11,
   "17": null,
   "Total": 113
 },
 {
   "Player": "",
   "1": null,
   "2": null,
   "3": null,
   "4": null,
   "5": null,
   "6": null,
   "7": null,
   "8": "",
   "9": null,
   "10": null,
   "11": null,
   "12": null,
   "13": null,
   "14": null,
   "15": null,
   "16": null,
   "17": null,
   "Total": null
 },
 {
   "Player": "Janoris Jenkins",
   "1": 78,
   "2": 59,
   "3": 71,
   "4": 74,
   "5": 77,
   "6": 83,
   "7": 78,
   "8": "",
   "9": 75,
   "10": 58,
   "11": 64,
   "12": 62,
   "13": 73,
   "14": 66,
   "15": 15,
   "16": null,
   "17": 23,
   "Total": 956
 },
 {
   "Player": "Keenan Robinson",
   "1": 30,
   "2": 52,
   "3": 46,
   "4": 44,
   "5": 66,
   "6": 61,
   "7": 67,
   "8": "",
   "9": 63,
   "10": 44,
   "11": 41,
   "12": 60,
   "13": 50,
   "14": 51,
   "15": 29,
   "16": 29,
   "17": 47,
   "Total": 780
 },
 {
   "Player": "",
   "1": null,
   "2": null,
   "3": null,
   "4": null,
   "5": null,
   "6": null,
   "7": null,
   "8": "",
   "9": null,
   "10": null,
   "11": null,
   "12": null,
   "13": null,
   "14": null,
   "15": null,
   "16": null,
   "17": null,
   "Total": null
 },
 {
   "Player": "Dominique Rodgers-Cromartie",
   "1": 77,
   "2": 39,
   "3": 32,
   "4": null,
   "5": 61,
   "6": 56,
   "7": 73,
   "8": "",
   "9": 59,
   "10": 14,
   "11": 34,
   "12": 49,
   "13": 44,
   "14": 35,
   "15": 59,
   "16": 55,
   "17": 46,
   "Total": 733
 },
 {
   "Player": "Ben Edwards",
   "1": 0,
   "2": 0,
   "3": 0,
   "4": 0,
   "5": null,
   "6": null,
   "7": null,
   "8": "",
   "9": null,
   "10": null,
   "11": null,
   "12": null,
   "13": null,
   "14": null,
   "15": null,
   "16": null,
   "17": null,
   "Total": 0
 },
 {
   "Player": "",
   "1": null,
   "2": null,
   "3": null,
   "4": null,
   "5": null,
   "6": null,
   "7": null,
   "8": "",
   "9": null,
   "10": null,
   "11": null,
   "12": null,
   "13": null,
   "14": null,
   "15": null,
   "16": null,
   "17": null,
   "Total": null
 }
]